ant_auto_tool_1/__init__.py
ant_auto_tool_1/isotonic_file.py
ant_auto_tool_1-0.1.2.dist-info/LICENSE
ant_auto_tool_1-0.1.2.dist-info/METADATA
ant_auto_tool_1-0.1.2.dist-info/WHEEL
ant_auto_tool_1-0.1.2.dist-info/top_level.txt
ant_auto_tool_1-0.1.2.dist-info/RECORD
