Metadata-Version: 2.2
Name: ant_auto_tool_1
Version: 0.1.2
Summary: A tool for ant auto
Home-page: 
Author: Pingchuan ZHONG
Author-email: zhongpingchuan.zpc@antgroup.com
Classifier: Programming Language :: Python :: 3
Classifier: License :: OSI Approved :: MIT License
Classifier: Operating System :: OS Independent
Requires-Python: >=3.5
License-File: LICENSE
Dynamic: author
Dynamic: author-email
Dynamic: classifier
Dynamic: description
Dynamic: description-content-type
Dynamic: requires-python
Dynamic: summary
